{
	"backtrace" : 2,
	"backtraceGraph" : 
	{
		"commands" : 
		[
			"add_custom_target",
			"mbed_set_linker_script"
		],
		"files" : 
		[
			"mbed-os/tools/cmake/mbed_set_linker_script.cmake",
			"mbed-os/targets/TARGET_NXP/TARGET_LPC11XX_11CXX/CMakeLists.txt"
		],
		"nodes" : 
		[
			{
				"file" : 1
			},
			{
				"command" : 1,
				"file" : 1,
				"line" : 44,
				"parent" : 0
			},
			{
				"command" : 0,
				"file" : 0,
				"line" : 37,
				"parent" : 1
			}
		]
	},
	"id" : "mbed-lpc1114LinkerScript::@a7d39c41994540d50cda",
	"name" : "mbed-lpc1114LinkerScript",
	"paths" : 
	{
		"build" : "mbed-os/targets/TARGET_NXP/TARGET_LPC11XX_11CXX",
		"source" : "mbed-os/targets/TARGET_NXP/TARGET_LPC11XX_11CXX"
	},
	"sourceGroups" : 
	[
		{
			"name" : "",
			"sourceIndexes" : 
			[
				0
			]
		},
		{
			"name" : "CMake Rules",
			"sourceIndexes" : 
			[
				1,
				2
			]
		}
	],
	"sources" : 
	[
		{
			"backtrace" : 2,
			"isGenerated" : true,
			"path" : "build/mbed-os/targets/TARGET_NXP/TARGET_LPC11XX_11CXX/CMakeFiles/mbed-lpc1114LinkerScript",
			"sourceGroupIndex" : 0
		},
		{
			"backtrace" : 0,
			"isGenerated" : true,
			"path" : "build/mbed-os/targets/TARGET_NXP/TARGET_LPC11XX_11CXX/CMakeFiles/mbed-lpc1114LinkerScript.rule",
			"sourceGroupIndex" : 1
		},
		{
			"backtrace" : 0,
			"isGenerated" : true,
			"path" : "build/mbed-os/targets/TARGET_NXP/TARGET_LPC11XX_11CXX/mbed-lpc1114.link_script.ld.rule",
			"sourceGroupIndex" : 1
		}
	],
	"type" : "UTILITY"
}
